[
  {
    "t": "11.8607",
    "h": "61.936"
  },
  {
    "t": "11.718",
    "h": "61.904"
  },
  {
    "t": "11.59",
    "h": "62.032"
  },
  {
    "t": "11.4713",
    "h": "62.0613"
  },
  {
    "t": "11.3627",
    "h": "62.1653"
  },
  {
    "t": "11.2193",
    "h": "62.4693"
  },
  {
    "t": "11.106",
    "h": "62.4773"
  },
  {
    "t": "11.016",
    "h": "62.7467"
  },
  {
    "t": "10.9633",
    "h": "63.3573"
  },
  {
    "t": "10.886",
    "h": "63.272"
  },
  {
    "t": "10.8067",
    "h": "62.8827"
  },
  {
    "t": "10.6967",
    "h": "63.5653"
  },
  {
    "t": "10.6067",
    "h": "63.6187"
  },
  {
    "t": "10.5633",
    "h": "63.832"
  },
  {
    "t": "10.4827",
    "h": "63.896"
  },
  {
    "t": "10.4133",
    "h": "63.6347"
  },
  {
    "t": "10.348",
    "h": "63.9547"
  },
  {
    "t": "10.2773",
    "h": "63.9333"
  },
  {
    "t": "10.238",
    "h": "64.6213"
  },
  {
    "t": "10.216",
    "h": "64.3973"
  },
  {
    "t": "10.254",
    "h": "64.1813"
  },
  {
    "t": "10.354",
    "h": "63.848"
  },
  {
    "t": "10.5533",
    "h": "63"
  },
  {
    "t": "10.786",
    "h": "61.9093"
  },
  {
    "t": "11.0813",
    "h": "61.1627"
  },
  {
    "t": "11.4247",
    "h": "60.7573"
  },
  {
    "t": "11.8167",
    "h": "60.5893"
  },
  {
    "t": "12.2353",
    "h": "60.5333"
  },
  {
    "t": "12.5967",
    "h": "60.6027"
  },
  {
    "t": "12.9733",
    "h": "60.688"
  },
  {
    "t": "13.422",
    "h": "60.9813"
  },
  {
    "t": "13.9173",
    "h": "60.7813"
  },
  {
    "t": "14.436",
    "h": "60.792"
  },
  {
    "t": "14.96",
    "h": "60.5093"
  },
  {
    "t": "15.4513",
    "h": "59.712"
  },
  {
    "t": "15.8667",
    "h": "58.9787"
  },
  {
    "t": "16.2513",
    "h": "58.512"
  },
  {
    "t": "16.6393",
    "h": "58.24"
  },
  {
    "t": "17.006",
    "h": "57.7467"
  },
  {
    "t": "17.328",
    "h": "57.2613"
  },
  {
    "t": "17.6527",
    "h": "56.9227"
  },
  {
    "t": "18.0187",
    "h": "56.624"
  },
  {
    "t": "18.398",
    "h": "56.5307"
  },
  {
    "t": "18.768",
    "h": "56.5893"
  },
  {
    "t": "19.0667",
    "h": "57.088"
  },
  {
    "t": "19.186",
    "h": "57.2533"
  },
  {
    "t": "19.378",
    "h": "57.4533"
  },
  {
    "t": "19.642",
    "h": "57.208"
  },
  {
    "t": "19.938",
    "h": "56.7973"
  },
  {
    "t": "20.0167",
    "h": "56.6693"
  },
  {
    "t": "20.154",
    "h": "57.08"
  },
  {
    "t": "20.3333",
    "h": "56.936"
  },
  {
    "t": "20.3873",
    "h": "56.848"
  },
  {
    "t": "20.3113",
    "h": "57.0827"
  },
  {
    "t": "20.186",
    "h": "57.4373"
  },
  {
    "t": "19.9567",
    "h": "58.104"
  },
  {
    "t": "19.7467",
    "h": "58.8267"
  },
  {
    "t": "19.4633",
    "h": "59.6"
  },
  {
    "t": "19.2573",
    "h": "60.568"
  },
  {
    "t": "19.042",
    "h": "61.3573"
  },
  {
    "t": "18.8587",
    "h": "61.6987"
  },
  {
    "t": "18.62",
    "h": "62.8427"
  },
  {
    "t": "18.3827",
    "h": "64.3387"
  },
  {
    "t": "18.166",
    "h": "65.4107"
  },
  {
    "t": "17.98",
    "h": "65.8347"
  },
  {
    "t": "17.8167",
    "h": "66.2533"
  },
  {
    "t": "17.6247",
    "h": "65.9333"
  },
  {
    "t": "17.3913",
    "h": "65.5493"
  },
  {
    "t": "17.2113",
    "h": "65.9093"
  },
  {
    "t": "17.018",
    "h": "66.704"
  },
  {
    "t": "16.8673",
    "h": "67.36"
  },
  {
    "t": "16.7107",
    "h": "68.2693"
  },
  {
    "t": "16.5567",
    "h": "68.7227"
  },
  {
    "t": "16.3973",
    "h": "68.9413"
  },
  {
    "t": "16.242",
    "h": "69.264"
  },
  {
    "t": "16.108",
    "h": "69.4853"
  },
  {
    "t": "16",
    "h": "69.7573"
  },
  {
    "t": "15.8847",
    "h": "70.3253"
  },
  {
    "t": "15.7813",
    "h": "70.632"
  },
  {
    "t": "15.6747",
    "h": "70.592"
  },
  {
    "t": "15.5433",
    "h": "70.5147"
  },
  {
    "t": "15.4007",
    "h": "70.288"
  },
  {
    "t": "15.2513",
    "h": "69.1333"
  },
  {
    "t": "15.07",
    "h": "68.864"
  },
  {
    "t": "14.9207",
    "h": "69.2747"
  },
  {
    "t": "14.7887",
    "h": "69.1253"
  },
  {
    "t": "14.6607",
    "h": "68.592"
  },
  {
    "t": "14.4713",
    "h": "68.296"
  },
  {
    "t": "14.3293",
    "h": "68.7893"
  },
  {
    "t": "14.2067",
    "h": "69.5627"
  },
  {
    "t": "14.108",
    "h": "69.664"
  },
  {
    "t": "13.9953",
    "h": "69.824"
  },
  {
    "t": "13.8813",
    "h": "69.9307"
  },
  {
    "t": "13.7087",
    "h": "70.0693"
  },
  {
    "t": "13.5353",
    "h": "69.8533"
  },
  {
    "t": "13.3427",
    "h": "69.9973"
  },
  {
    "t": "13.2053",
    "h": "70.0827"
  },
  {
    "t": "13.07",
    "h": "69.896"
  },
  {
    "t": "12.952",
    "h": "69.44"
  },
  {
    "t": "12.836",
    "h": "69.2293"
  },
  {
    "t": "12.712",
    "h": "69.4027"
  },
  {
    "t": "12.584",
    "h": "69.1707"
  },
  {
    "t": "12.4647",
    "h": "68.7733"
  },
  {
    "t": "12.34",
    "h": "68.7867"
  },
  {
    "t": "12.1733",
    "h": "68.992"
  },
  {
    "t": "12.0573",
    "h": "69.2667"
  },
  {
    "t": "11.97",
    "h": "69.6133"
  },
  {
    "t": "11.8767",
    "h": "69.6853"
  },
  {
    "t": "11.76",
    "h": "69.5467"
  },
  {
    "t": "11.6507",
    "h": "68.592"
  },
  {
    "t": "11.524",
    "h": "68.1893"
  },
  {
    "t": "11.4447",
    "h": "68.5173"
  },
  {
    "t": "11.3547",
    "h": "68.5893"
  },
  {
    "t": "11.27",
    "h": "68.3653"
  },
  {
    "t": "11.19",
    "h": "68.2853"
  },
  {
    "t": "11.1233",
    "h": "68.44"
  },
  {
    "t": "11.1167",
    "h": "68.5013"
  },
  {
    "t": "11.1833",
    "h": "68.2987"
  },
  {
    "t": "11.3327",
    "h": "68.0907"
  },
  {
    "t": "11.5187",
    "h": "67.0907"
  },
  {
    "t": "11.764",
    "h": "65.824"
  },
  {
    "t": "12.1273",
    "h": "65.0747"
  },
  {
    "t": "12.5267",
    "h": "64.9493"
  },
  {
    "t": "12.9487",
    "h": "64.904"
  },
  {
    "t": "13.4147",
    "h": "64.8053"
  },
  {
    "t": "13.8907",
    "h": "64.4987"
  },
  {
    "t": "14.312",
    "h": "64.0773"
  },
  {
    "t": "14.7493",
    "h": "63.6613"
  },
  {
    "t": "15.17",
    "h": "63.144"
  },
  {
    "t": "15.568",
    "h": "62.6907"
  },
  {
    "t": "16.002",
    "h": "62.1147"
  },
  {
    "t": "16.3973",
    "h": "61.8907"
  },
  {
    "t": "16.828",
    "h": "61.464"
  },
  {
    "t": "17.2213",
    "h": "60.936"
  },
  {
    "t": "17.6093",
    "h": "60.2933"
  },
  {
    "t": "17.9693",
    "h": "59.408"
  },
  {
    "t": "18.2487",
    "h": "58.6533"
  },
  {
    "t": "18.3767",
    "h": "57.5333"
  },
  {
    "t": "18.3233",
    "h": "56.6507"
  },
  {
    "t": "18.3733",
    "h": "57.552"
  },
  {
    "t": "18.658",
    "h": "55.704"
  },
  {
    "t": "18.8773",
    "h": "53.8"
  },
  {
    "t": "19.1333",
    "h": "53.5253"
  },
  {
    "t": "19.194",
    "h": "49.832"
  },
  {
    "t": "18.934",
    "h": "49.8827"
  },
  {
    "t": "18.784",
    "h": "50.6453"
  },
  {
    "t": "18.6533",
    "h": "50.5093"
  },
  {
    "t": "18.574",
    "h": "50.816"
  },
  {
    "t": "18.5953",
    "h": "51.408"
  },
  {
    "t": "18.7773",
    "h": "51.9307"
  },
  {
    "t": "18.8633",
    "h": "52.096"
  },
  {
    "t": "18.7627",
    "h": "51.88"
  },
  {
    "t": "18.6293",
    "h": "51.8587"
  },
  {
    "t": "18.53",
    "h": "52.1253"
  },
  {
    "t": "18.4587",
    "h": "52.3253"
  },
  {
    "t": "18.352",
    "h": "52.792"
  },
  {
    "t": "18.2573",
    "h": "52.7733"
  },
  {
    "t": "18.1253",
    "h": "52.5307"
  },
  {
    "t": "17.984",
    "h": "53.4747"
  },
  {
    "t": "17.846",
    "h": "53.832"
  },
  {
    "t": "17.7133",
    "h": "55.4053"
  },
  {
    "t": "17.5607",
    "h": "56.936"
  },
  {
    "t": "17.4433",
    "h": "57.8187"
  },
  {
    "t": "17.2827",
    "h": "58.2"
  },
  {
    "t": "17.1333",
    "h": "59"
  },
  {
    "t": "16.9807",
    "h": "60.1867"
  },
  {
    "t": "16.842",
    "h": "60.76"
  },
  {
    "t": "16.7133",
    "h": "61.1093"
  },
  {
    "t": "16.578",
    "h": "61.6187"
  },
  {
    "t": "16.4253",
    "h": "62.2533"
  },
  {
    "t": "16.238",
    "h": "62.4747"
  },
  {
    "t": "16.1093",
    "h": "62.264"
  },
  {
    "t": "15.972",
    "h": "62.112"
  },
  {
    "t": "15.822",
    "h": "61.984"
  },
  {
    "t": "15.6853",
    "h": "62.1013"
  },
  {
    "t": "15.5353",
    "h": "62.272"
  },
  {
    "t": "15.39",
    "h": "62.432"
  },
  {
    "t": "15.248",
    "h": "61.9627"
  },
  {
    "t": "15.0767",
    "h": "61.408"
  },
  {
    "t": "14.874",
    "h": "61.112"
  },
  {
    "t": "14.7447",
    "h": "61.176"
  },
  {
    "t": "14.6433",
    "h": "62.1787"
  },
  {
    "t": "14.5327",
    "h": "62.0667"
  },
  {
    "t": "14.3327",
    "h": "62.5813"
  },
  {
    "t": "14.0913",
    "h": "63.152"
  },
  {
    "t": "13.9453",
    "h": "63.216"
  },
  {
    "t": "13.7813",
    "h": "62.856"
  },
  {
    "t": "13.6193",
    "h": "62.72"
  },
  {
    "t": "13.47",
    "h": "62.656"
  },
  {
    "t": "13.3513",
    "h": "62.624"
  },
  {
    "t": "13.2233",
    "h": "62.6347"
  },
  {
    "t": "13.056",
    "h": "62.68"
  },
  {
    "t": "12.91",
    "h": "63.104"
  },
  {
    "t": "12.806",
    "h": "62.888"
  },
  {
    "t": "12.6933",
    "h": "62.8853"
  },
  {
    "t": "12.586",
    "h": "63.1547"
  },
  {
    "t": "12.4353",
    "h": "63.0667"
  },
  {
    "t": "12.3167",
    "h": "63.3467"
  },
  {
    "t": "12.2313",
    "h": "63.5093"
  },
  {
    "t": "12.1133",
    "h": "63.624"
  },
  {
    "t": "12.0053",
    "h": "63.5493"
  },
  {
    "t": "11.8887",
    "h": "63.6267"
  },
  {
    "t": "11.7887",
    "h": "63.688"
  },
  {
    "t": "11.6793",
    "h": "63.9467"
  },
  {
    "t": "11.63",
    "h": "64.024"
  },
  {
    "t": "11.5527",
    "h": "63.944"
  },
  {
    "t": "11.454",
    "h": "63.9333"
  },
  {
    "t": "11.3867",
    "h": "63.8213"
  },
  {
    "t": "11.286",
    "h": "63.568"
  },
  {
    "t": "11.202",
    "h": "63.6693"
  },
  {
    "t": "11.1133",
    "h": "63.8347"
  },
  {
    "t": "11.07",
    "h": "63.8347"
  },
  {
    "t": "11.1133",
    "h": "63.6747"
  },
  {
    "t": "11.23",
    "h": "63.6267"
  },
  {
    "t": "11.41",
    "h": "62.768"
  },
  {
    "t": "11.6513",
    "h": "61.632"
  },
  {
    "t": "11.9873",
    "h": "60.8853"
  },
  {
    "t": "12.3907",
    "h": "60.6107"
  },
  {
    "t": "12.8353",
    "h": "60.816"
  },
  {
    "t": "13.328",
    "h": "60.832"
  },
  {
    "t": "13.8167",
    "h": "60.9093"
  },
  {
    "t": "14.322",
    "h": "61"
  },
  {
    "t": "14.8433",
    "h": "60.632"
  },
  {
    "t": "15.344",
    "h": "60.4027"
  },
  {
    "t": "15.8113",
    "h": "59.872"
  },
  {
    "t": "16.28",
    "h": "59.4107"
  },
  {
    "t": "16.7313",
    "h": "58.8587"
  },
  {
    "t": "17.2267",
    "h": "58.272"
  },
  {
    "t": "17.7033",
    "h": "57.912"
  },
  {
    "t": "18.1967",
    "h": "57.3227"
  },
  {
    "t": "18.6027",
    "h": "56.432"
  },
  {
    "t": "18.934",
    "h": "55.6507"
  },
  {
    "t": "19.2733",
    "h": "55.008"
  },
  {
    "t": "19.59",
    "h": "54.3813"
  },
  {
    "t": "19.9193",
    "h": "53.1067"
  },
  {
    "t": "20.218",
    "h": "52.5387"
  },
  {
    "t": "20.5507",
    "h": "52.0027"
  },
  {
    "t": "20.92",
    "h": "51.6213"
  },
  {
    "t": "21.2613",
    "h": "51.0587"
  },
  {
    "t": "21.5413",
    "h": "50.24"
  },
  {
    "t": "21.7827",
    "h": "49.904"
  },
  {
    "t": "22.0053",
    "h": "49.3733"
  },
  {
    "t": "22.1587",
    "h": "48.2373"
  },
  {
    "t": "22.232",
    "h": "47.424"
  },
  {
    "t": "22.2053",
    "h": "46.9947"
  },
  {
    "t": "22.212",
    "h": "47.9253"
  },
  {
    "t": "22.1333",
    "h": "47.5307"
  },
  {
    "t": "21.896",
    "h": "46.9653"
  },
  {
    "t": "21.5947",
    "h": "46.8293"
  },
  {
    "t": "21.22",
    "h": "47.2053"
  },
  {
    "t": "20.896",
    "h": "47.5227"
  },
  {
    "t": "20.5813",
    "h": "47.6453"
  },
  {
    "t": "20.2467",
    "h": "48.2347"
  },
  {
    "t": "19.9193",
    "h": "48.7147"
  },
  {
    "t": "19.6307",
    "h": "49.24"
  },
  {
    "t": "19.3953",
    "h": "49.68"
  },
  {
    "t": "19.1293",
    "h": "49.832"
  },
  {
    "t": "18.8733",
    "h": "51.6507"
  },
  {
    "t": "18.6447",
    "h": "53.7253"
  },
  {
    "t": "18.3707",
    "h": "54.84"
  },
  {
    "t": "18.1453",
    "h": "56"
  },
  {
    "t": "17.914",
    "h": "57.2213"
  },
  {
    "t": "17.7",
    "h": "58.1867"
  },
  {
    "t": "17.4927",
    "h": "59.0987"
  },
  {
    "t": "17.2827",
    "h": "59.5707"
  },
  {
    "t": "17.1027",
    "h": "59.8213"
  },
  {
    "t": "16.8927",
    "h": "60.5067"
  },
  {
    "t": "16.6993",
    "h": "60.968"
  },
  {
    "t": "16.5067",
    "h": "60.88"
  },
  {
    "t": "16.294",
    "h": "61.296"
  },
  {
    "t": "16.1053",
    "h": "62.0373"
  },
  {
    "t": "15.9767",
    "h": "61.752"
  },
  {
    "t": "15.8047",
    "h": "61.4613"
  },
  {
    "t": "15.5867",
    "h": "60.9813"
  },
  {
    "t": "15.362",
    "h": "60.512"
  },
  {
    "t": "15.1233",
    "h": "59.8373"
  },
  {
    "t": "14.91",
    "h": "59.3493"
  },
  {
    "t": "14.732",
    "h": "59.7387"
  },
  {
    "t": "14.5273",
    "h": "59.4347"
  },
  {
    "t": "14.3653",
    "h": "59.9093"
  },
  {
    "t": "14.1973",
    "h": "59.888"
  },
  {
    "t": "14.01",
    "h": "59.1147"
  },
  {
    "t": "13.8113",
    "h": "57.736"
  },
  {
    "t": "13.6393",
    "h": "57.528"
  },
  {
    "t": "13.4513",
    "h": "57.7467"
  },
  {
    "t": "13.2973",
    "h": "57.9467"
  },
  {
    "t": "13.1373",
    "h": "57.8773"
  },
  {
    "t": "12.96",
    "h": "57.8133"
  },
  {
    "t": "12.7933",
    "h": "57.8267"
  },
  {
    "t": "12.6253",
    "h": "57.6747"
  },
  {
    "t": "12.4687",
    "h": "57.5413"
  },
  {
    "t": "12.3513",
    "h": "57.2213"
  },
  {
    "t": "12.2527",
    "h": "56.1947"
  },
  {
    "t": "12.1333",
    "h": "55.5493"
  },
  {
    "t": "12.042",
    "h": "55.1573"
  },
  {
    "t": "11.96",
    "h": "55.2053"
  },
  {
    "t": "11.85",
    "h": "55.288"
  },
  {
    "t": "11.74",
    "h": "55.3067"
  },
  {
    "t": "11.636",
    "h": "55.4907"
  },
  {
    "t": "11.5153",
    "h": "55.4853"
  },
  {
    "t": "11.4287",
    "h": "55.44"
  },
  {
    "t": "11.324",
    "h": "55.4187"
  },
  {
    "t": "11.242",
    "h": "55.408"
  },
  {
    "t": "11.0633",
    "h": "56.432"
  },
  {
    "t": "10.8673",
    "h": "56.7227"
  },
  {
    "t": "10.7287",
    "h": "56.9653"
  },
  {
    "t": "10.6333",
    "h": "57.4827"
  },
  {
    "t": "10.6433",
    "h": "57.264"
  },
  {
    "t": "10.696",
    "h": "57.448"
  },
  {
    "t": "10.8647",
    "h": "56.824"
  },
  {
    "t": "11.0873",
    "h": "56.1893"
  },
  {
    "t": "11.43",
    "h": "55.496"
  },
  {
    "t": "11.8627",
    "h": "55.3653"
  },
  {
    "t": "12.3153",
    "h": "55.7467"
  },
  {
    "t": "12.7853",
    "h": "55.944"
  },
  {
    "t": "13.2667",
    "h": "56.1253"
  },
  {
    "t": "13.7567",
    "h": "56.1067"
  },
  {
    "t": "14.312",
    "h": "55.6853"
  },
  {
    "t": "14.8027",
    "h": "54.9973"
  },
  {
    "t": "15.3267",
    "h": "54.3413"
  },
  {
    "t": "15.8347",
    "h": "53.7653"
  },
  {
    "t": "16.3433",
    "h": "53.2853"
  },
  {
    "t": "16.8607",
    "h": "52.6373"
  },
  {
    "t": "17.3333",
    "h": "52.2507"
  },
  {
    "t": "17.8073",
    "h": "51.9333"
  },
  {
    "t": "18.232",
    "h": "51.544"
  },
  {
    "t": "18.67",
    "h": "50.9493"
  },
  {
    "t": "19.1053",
    "h": "50.5973"
  },
  {
    "t": "19.4993",
    "h": "50.504"
  },
  {
    "t": "19.9227",
    "h": "49.9253"
  },
  {
    "t": "20.38",
    "h": "49.4933"
  },
  {
    "t": "20.8053",
    "h": "48.9867"
  },
  {
    "t": "21.1907",
    "h": "48.592"
  },
  {
    "t": "21.564",
    "h": "48.2507"
  },
  {
    "t": "21.9093",
    "h": "47.7893"
  },
  {
    "t": "22.2493",
    "h": "46.9707"
  },
  {
    "t": "22.596",
    "h": "46.52"
  },
  {
    "t": "22.9147",
    "h": "45.56"
  },
  {
    "t": "23.048",
    "h": "45.432"
  },
  {
    "t": "23.176",
    "h": "44.9867"
  },
  {
    "t": "23.256",
    "h": "44.176"
  },
  {
    "t": "23.1787",
    "h": "43.2773"
  },
  {
    "t": "23.0067",
    "h": "42.1413"
  },
  {
    "t": "22.832",
    "h": "42.456"
  },
  {
    "t": "22.588",
    "h": "41.8267"
  },
  {
    "t": "22.22",
    "h": "42.2773"
  },
  {
    "t": "21.7907",
    "h": "43.2507"
  },
  {
    "t": "21.468",
    "h": "44.968"
  },
  {
    "t": "21.1187",
    "h": "46.1333"
  },
  {
    "t": "20.828",
    "h": "48.7947"
  },
  {
    "t": "20.5747",
    "h": "51.2773"
  },
  {
    "t": "20.3393",
    "h": "52.7387"
  },
  {
    "t": "20.1373",
    "h": "53.6"
  },
  {
    "t": "19.9153",
    "h": "54.4667"
  },
  {
    "t": "19.6753",
    "h": "55.1467"
  },
  {
    "t": "19.4427",
    "h": "56.2933"
  },
  {
    "t": "19.1967",
    "h": "57.2907"
  },
  {
    "t": "18.984",
    "h": "57.8933"
  },
  {
    "t": "18.76",
    "h": "58.3227"
  },
  {
    "t": "18.5293",
    "h": "58.6213"
  },
  {
    "t": "18.306",
    "h": "58.9333"
  },
  {
    "t": "18.09",
    "h": "59.176"
  },
  {
    "t": "17.8693",
    "h": "59.576"
  },
  {
    "t": "17.66",
    "h": "60"
  },
  {
    "t": "17.4333",
    "h": "60.3573"
  },
  {
    "t": "17.248",
    "h": "60.704"
  },
  {
    "t": "17.066",
    "h": "61.0267"
  },
  {
    "t": "16.888",
    "h": "61.0933"
  },
  {
    "t": "16.7307",
    "h": "61.2533"
  },
  {
    "t": "16.5673",
    "h": "61.6613"
  },
  {
    "t": "16.3973",
    "h": "61.8453"
  },
  {
    "t": "16.1967",
    "h": "61.544"
  },
  {
    "t": "16.0127",
    "h": "61.4533"
  },
  {
    "t": "15.836",
    "h": "61.5387"
  },
  {
    "t": "15.666",
    "h": "61.6053"
  },
  {
    "t": "15.4927",
    "h": "61.7573"
  },
  {
    "t": "15.3547",
    "h": "61.4907"
  },
  {
    "t": "15.2013",
    "h": "61.4747"
  },
  {
    "t": "15.0387",
    "h": "61.2373"
  },
  {
    "t": "14.88",
    "h": "61.0773"
  },
  {
    "t": "14.7313",
    "h": "60.8747"
  },
  {
    "t": "14.5607",
    "h": "60.8347"
  },
  {
    "t": "14.358",
    "h": "60.96"
  },
  {
    "t": "14.1847",
    "h": "60.8587"
  },
  {
    "t": "14.0347",
    "h": "60.7147"
  },
  {
    "t": "13.91",
    "h": "60.8293"
  },
  {
    "t": "13.7967",
    "h": "60.5387"
  },
  {
    "t": "13.6407",
    "h": "60.496"
  },
  {
    "t": "13.5033",
    "h": "60.432"
  },
  {
    "t": "13.3907",
    "h": "60.3253"
  },
  {
    "t": "13.2767",
    "h": "60.216"
  },
  {
    "t": "13.1447",
    "h": "60.192"
  },
  {
    "t": "13.0093",
    "h": "60.2853"
  },
  {
    "t": "12.8993",
    "h": "60.2587"
  },
  {
    "t": "12.7953",
    "h": "60.2187"
  },
  {
    "t": "12.6793",
    "h": "60.2933"
  },
  {
    "t": "12.5767",
    "h": "60.232"
  },
  {
    "t": "12.4733",
    "h": "60.3627"
  },
  {
    "t": "12.382",
    "h": "60.384"
  },
  {
    "t": "12.256",
    "h": "60.4213"
  },
  {
    "t": "12.1433",
    "h": "60.3787"
  },
  {
    "t": "12.076",
    "h": "60.3547"
  },
  {
    "t": "11.9933",
    "h": "60.4053"
  },
  {
    "t": "11.96",
    "h": "60.4053"
  },
  {
    "t": "11.9667",
    "h": "60.4347"
  },
  {
    "t": "12.052",
    "h": "60.5787"
  },
  {
    "t": "12.1593",
    "h": "60.392"
  },
  {
    "t": "12.408",
    "h": "59.0667"
  },
  {
    "t": "12.8507",
    "h": "57.9627"
  },
  {
    "t": "13.236",
    "h": "57.688"
  },
  {
    "t": "13.7007",
    "h": "57.9333"
  },
  {
    "t": "14.1867",
    "h": "57.632"
  },
  {
    "t": "14.7087",
    "h": "57.04"
  },
  {
    "t": "15.2087",
    "h": "56.2933"
  },
  {
    "t": "15.7507",
    "h": "55.72"
  },
  {
    "t": "16.276",
    "h": "54.808"
  },
  {
    "t": "16.7673",
    "h": "54.056"
  },
  {
    "t": "17.316",
    "h": "53.2133"
  },
  {
    "t": "17.756",
    "h": "52.5147"
  },
  {
    "t": "18.1367",
    "h": "52.3467"
  },
  {
    "t": "18.4673",
    "h": "52.1333"
  },
  {
    "t": "18.8313",
    "h": "51.6827"
  },
  {
    "t": "19.212",
    "h": "51.1387"
  },
  {
    "t": "19.5607",
    "h": "50.5387"
  },
  {
    "t": "19.894",
    "h": "50.4293"
  },
  {
    "t": "20.1793",
    "h": "50.104"
  },
  {
    "t": "20.4413",
    "h": "49.8267"
  },
  {
    "t": "20.62",
    "h": "49.0773"
  },
  {
    "t": "20.824",
    "h": "49.0933"
  },
  {
    "t": "21.0227",
    "h": "48.3333"
  },
  {
    "t": "21.2227",
    "h": "48.352"
  },
  {
    "t": "21.4627",
    "h": "48.1653"
  },
  {
    "t": "21.656",
    "h": "48.2507"
  },
  {
    "t": "21.832",
    "h": "48.3573"
  },
  {
    "t": "21.9693",
    "h": "47.4987"
  },
  {
    "t": "22.0213",
    "h": "47.3893"
  },
  {
    "t": "22.0027",
    "h": "47.7013"
  },
  {
    "t": "21.904",
    "h": "48.2053"
  },
  {
    "t": "21.8493",
    "h": "48.144"
  },
  {
    "t": "21.6547",
    "h": "48.5813"
  },
  {
    "t": "21.3973",
    "h": "49.6133"
  },
  {
    "t": "21.0667",
    "h": "50.112"
  },
  {
    "t": "20.7693",
    "h": "50.5547"
  },
  {
    "t": "20.4487",
    "h": "50.8347"
  },
  {
    "t": "20.1433",
    "h": "51.6587"
  },
  {
    "t": "19.852",
    "h": "52.12"
  },
  {
    "t": "19.588",
    "h": "52.872"
  },
  {
    "t": "19.3907",
    "h": "53.416"
  },
  {
    "t": "19.1973",
    "h": "53.784"
  },
  {
    "t": "18.9413",
    "h": "54.104"
  },
  {
    "t": "18.732",
    "h": "55.464"
  },
  {
    "t": "18.5253",
    "h": "57.144"
  },
  {
    "t": "18.2847",
    "h": "58.3467"
  },
  {
    "t": "18.1053",
    "h": "58.848"
  },
  {
    "t": "17.8773",
    "h": "59.3973"
  },
  {
    "t": "17.678",
    "h": "59.5387"
  },
  {
    "t": "17.5213",
    "h": "59.5173"
  },
  {
    "t": "17.3213",
    "h": "60.6213"
  },
  {
    "t": "17.1453",
    "h": "61.512"
  },
  {
    "t": "16.9813",
    "h": "62.0133"
  },
  {
    "t": "16.828",
    "h": "61.8507"
  },
  {
    "t": "16.6707",
    "h": "61.344"
  },
  {
    "t": "16.5413",
    "h": "61.0827"
  },
  {
    "t": "16.3867",
    "h": "60.9893"
  },
  {
    "t": "16.2407",
    "h": "60.7013"
  },
  {
    "t": "16.0807",
    "h": "61.2933"
  },
  {
    "t": "15.9347",
    "h": "61.7333"
  },
  {
    "t": "15.7887",
    "h": "60.928"
  },
  {
    "t": "15.6247",
    "h": "60.5627"
  },
  {
    "t": "15.454",
    "h": "60.6773"
  },
  {
    "t": "15.316",
    "h": "60.464"
  },
  {
    "t": "15.1733",
    "h": "60.3413"
  },
  {
    "t": "15.0313",
    "h": "60.1787"
  },
  {
    "t": "14.886",
    "h": "60.3013"
  },
  {
    "t": "14.7507",
    "h": "60.1547"
  },
  {
    "t": "14.6427",
    "h": "59.9413"
  },
  {
    "t": "14.4607",
    "h": "60.168"
  },
  {
    "t": "14.3293",
    "h": "60.1467"
  },
  {
    "t": "14.2333",
    "h": "59.7627"
  },
  {
    "t": "14.0773",
    "h": "59.712"
  },
  {
    "t": "13.938",
    "h": "59.8987"
  },
  {
    "t": "13.8033",
    "h": "60.152"
  },
  {
    "t": "13.7047",
    "h": "60.3307"
  },
  {
    "t": "13.5913",
    "h": "60.5067"
  },
  {
    "t": "13.4893",
    "h": "60.6293"
  },
  {
    "t": "13.358",
    "h": "60.776"
  },
  {
    "t": "13.2533",
    "h": "61.0213"
  },
  {
    "t": "13.1967",
    "h": "61.3733"
  },
  {
    "t": "13.122",
    "h": "61.0933"
  },
  {
    "t": "13.0467",
    "h": "60.9787"
  },
  {
    "t": "12.9573",
    "h": "60.896"
  },
  {
    "t": "12.858",
    "h": "60.424"
  },
  {
    "t": "12.7767",
    "h": "60.0293"
  },
  {
    "t": "12.684",
    "h": "59.896"
  },
  {
    "t": "12.6267",
    "h": "59.8"
  },
  {
    "t": "12.5393",
    "h": "59.7493"
  },
  {
    "t": "12.438",
    "h": "59.7867"
  },
  {
    "t": "12.354",
    "h": "59.6213"
  },
  {
    "t": "12.31",
    "h": "59.4773"
  },
  {
    "t": "12.29",
    "h": "59.2613"
  },
  {
    "t": "12.366",
    "h": "58.9307"
  },
  {
    "t": "12.4867",
    "h": "58.656"
  },
  {
    "t": "12.6813",
    "h": "58.2373"
  },
  {
    "t": "12.9033",
    "h": "57.5467"
  },
  {
    "t": "13.256",
    "h": "57"
  },
  {
    "t": "13.6387",
    "h": "56.9467"
  },
  {
    "t": "14.0593",
    "h": "56.904"
  },
  {
    "t": "14.532",
    "h": "56.8373"
  },
  {
    "t": "15.0313",
    "h": "56.4027"
  },
  {
    "t": "15.524",
    "h": "55.952"
  },
  {
    "t": "16.0493",
    "h": "54.8187"
  },
  {
    "t": "16.5493",
    "h": "53.712"
  },
  {
    "t": "17.024",
    "h": "52.9253"
  },
  {
    "t": "17.452",
    "h": "52.0613"
  },
  {
    "t": "17.874",
    "h": "51.3973"
  },
  {
    "t": "18.256",
    "h": "50.6853"
  },
  {
    "t": "18.712",
    "h": "49.9253"
  },
  {
    "t": "19.1333",
    "h": "49"
  },
  {
    "t": "19.482",
    "h": "48.5893"
  },
  {
    "t": "19.7773",
    "h": "47.9973"
  },
  {
    "t": "20.1333",
    "h": "47.5947"
  },
  {
    "t": "20.436",
    "h": "46.96"
  },
  {
    "t": "20.7227",
    "h": "46.7893"
  },
  {
    "t": "21.0653",
    "h": "46.0453"
  },
  {
    "t": "21.3573",
    "h": "45.144"
  },
  {
    "t": "21.5947",
    "h": "44.3973"
  },
  {
    "t": "21.8453",
    "h": "44.232"
  },
  {
    "t": "22.2013",
    "h": "44.248"
  },
  {
    "t": "22.4387",
    "h": "42.6853"
  },
  {
    "t": "22.6973",
    "h": "42.7067"
  },
  {
    "t": "22.9133",
    "h": "42.5067"
  },
  {
    "t": "23.076",
    "h": "41.728"
  },
  {
    "t": "23.1",
    "h": "39.8867"
  },
  {
    "t": "23.056",
    "h": "39.6787"
  },
  {
    "t": "22.9693",
    "h": "38.728"
  },
  {
    "t": "22.796",
    "h": "38.1493"
  },
  {
    "t": "22.568",
    "h": "38.292"
  },
  {
    "t": "22.2493",
    "h": "38.4067"
  },
  {
    "t": "21.904",
    "h": "38.7827"
  },
  {
    "t": "21.572",
    "h": "39.216"
  },
  {
    "t": "21.24",
    "h": "39.7853"
  },
  {
    "t": "20.9773",
    "h": "40.5587"
  },
  {
    "t": "20.696",
    "h": "40.7987"
  },
  {
    "t": "20.4373",
    "h": "41.736"
  },
  {
    "t": "20.2153",
    "h": "43.4693"
  },
  {
    "t": "20.0133",
    "h": "45.3787"
  },
  {
    "t": "19.7807",
    "h": "48.352"
  },
  {
    "t": "19.5553",
    "h": "50.488"
  },
  {
    "t": "19.3647",
    "h": "52.624"
  },
  {
    "t": "19.1393",
    "h": "53.92"
  },
  {
    "t": "18.8913",
    "h": "55.288"
  },
  {
    "t": "18.7073",
    "h": "56.1147"
  },
  {
    "t": "18.496",
    "h": "56.824"
  },
  {
    "t": "18.278",
    "h": "57.768"
  },
  {
    "t": "18.0987",
    "h": "58.4667"
  },
  {
    "t": "17.9373",
    "h": "58.9227"
  },
  {
    "t": "17.7713",
    "h": "59.4533"
  },
  {
    "t": "17.5993",
    "h": "59.9627"
  },
  {
    "t": "17.4293",
    "h": "59.5333"
  },
  {
    "t": "17.206",
    "h": "57.4133"
  },
  {
    "t": "16.944",
    "h": "55.712"
  },
  {
    "t": "16.6713",
    "h": "54.2987"
  },
  {
    "t": "16.362",
    "h": "54.0453"
  },
  {
    "t": "16.106",
    "h": "53.2507"
  },
  {
    "t": "15.93",
    "h": "52.4107"
  },
  {
    "t": "15.75",
    "h": "51.5253"
  },
  {
    "t": "15.5787",
    "h": "51.3013"
  },
  {
    "t": "15.386",
    "h": "50.848"
  },
  {
    "t": "15.176",
    "h": "50.5573"
  },
  {
    "t": "15.0247",
    "h": "50.248"
  },
  {
    "t": "14.8427",
    "h": "50.8693"
  },
  {
    "t": "14.6353",
    "h": "51.3333"
  },
  {
    "t": "14.4933",
    "h": "51.344"
  },
  {
    "t": "14.3553",
    "h": "51.2667"
  },
  {
    "t": "14.2007",
    "h": "51.2907"
  },
  {
    "t": "14.0567",
    "h": "51.4827"
  },
  {
    "t": "13.9173",
    "h": "51.2507"
  },
  {
    "t": "13.7647",
    "h": "51.568"
  },
  {
    "t": "13.6273",
    "h": "51.4853"
  },
  {
    "t": "13.512",
    "h": "51.4853"
  },
  {
    "t": "13.3873",
    "h": "51.5947"
  },
  {
    "t": "13.27",
    "h": "51.7067"
  },
  {
    "t": "13.1847",
    "h": "51.8773"
  },
  {
    "t": "13.0593",
    "h": "52.1387"
  },
  {
    "t": "12.9447",
    "h": "52.0747"
  },
  {
    "t": "12.8167",
    "h": "52.1387"
  },
  {
    "t": "12.7333",
    "h": "52.16"
  },
  {
    "t": "12.6947",
    "h": "52.072"
  },
  {
    "t": "12.6133",
    "h": "52.1307"
  },
  {
    "t": "12.582",
    "h": "51.88"
  },
  {
    "t": "12.5027",
    "h": "51.8"
  },
  {
    "t": "12.352",
    "h": "52.4213"
  },
  {
    "t": "12.162",
    "h": "53.08"
  },
  {
    "t": "12.0307",
    "h": "53.24"
  },
  {
    "t": "11.9867",
    "h": "53.224"
  },
  {
    "t": "12.014",
    "h": "53.008"
  },
  {
    "t": "12.0747",
    "h": "53.12"
  },
  {
    "t": "12.216",
    "h": "52.8373"
  },
  {
    "t": "12.4213",
    "h": "52.472"
  },
  {
    "t": "12.698",
    "h": "51.8373"
  },
  {
    "t": "13.08",
    "h": "51.088"
  },
  {
    "t": "13.498",
    "h": "50.6267"
  },
  {
    "t": "13.9673",
    "h": "50.424"
  },
  {
    "t": "14.4753",
    "h": "49.9093"
  },
  {
    "t": "14.9893",
    "h": "49.24"
  },
  {
    "t": "15.4187",
    "h": "48.352"
  },
  {
    "t": "15.868",
    "h": "47.872"
  },
  {
    "t": "16.3873",
    "h": "47.4"
  },
  {
    "t": "16.9673",
    "h": "46.816"
  },
  {
    "t": "17.494",
    "h": "46.0693"
  },
  {
    "t": "18.066",
    "h": "44.9653"
  },
  {
    "t": "18.6827",
    "h": "44.9413"
  },
  {
    "t": "19.208",
    "h": "44.5573"
  },
  {
    "t": "19.654",
    "h": "44.088"
  },
  {
    "t": "20.0633",
    "h": "43.584"
  },
  {
    "t": "20.4687",
    "h": "43.2267"
  },
  {
    "t": "20.848",
    "h": "43.1093"
  },
  {
    "t": "21.2573",
    "h": "42.3013"
  },
  {
    "t": "21.6627",
    "h": "42.0187"
  },
  {
    "t": "21.9707",
    "h": "40.7907"
  },
  {
    "t": "22.38",
    "h": "40.7373"
  },
  {
    "t": "22.8227",
    "h": "39.5907"
  },
  {
    "t": "23.1773",
    "h": "39.1173"
  },
  {
    "t": "23.5693",
    "h": "38.5293"
  },
  {
    "t": "23.828",
    "h": "37.9133"
  },
  {
    "t": "24.0907",
    "h": "37.772"
  },
  {
    "t": "24.36",
    "h": "37.536"
  },
  {
    "t": "24.58",
    "h": "36.6147"
  },
  {
    "t": "24.6467",
    "h": "36.092"
  },
  {
    "t": "24.712",
    "h": "35.4573"
  },
  {
    "t": "24.6587",
    "h": "34.3933"
  },
  {
    "t": "24.508",
    "h": "33.4467"
  },
  {
    "t": "24.2373",
    "h": "32.3093"
  },
  {
    "t": "23.8267",
    "h": "31.104"
  },
  {
    "t": "23.3893",
    "h": "31.2613"
  },
  {
    "t": "23.0053",
    "h": "31.3973"
  },
  {
    "t": "22.7",
    "h": "31.4347"
  },
  {
    "t": "22.3987",
    "h": "31.984"
  },
  {
    "t": "22.1107",
    "h": "33.012"
  },
  {
    "t": "21.848",
    "h": "33.72"
  },
  {
    "t": "21.556",
    "h": "35.868"
  },
  {
    "t": "21.2853",
    "h": "37.7987"
  },
  {
    "t": "20.972",
    "h": "40.3587"
  },
  {
    "t": "20.664",
    "h": "42.3147"
  },
  {
    "t": "20.3993",
    "h": "43.416"
  },
  {
    "t": "20.1467",
    "h": "44.04"
  },
  {
    "t": "19.8973",
    "h": "44.9147"
  },
  {
    "t": "19.6527",
    "h": "45.3573"
  },
  {
    "t": "19.4153",
    "h": "45.7067"
  },
  {
    "t": "19.186",
    "h": "45.4667"
  },
  {
    "t": "18.9307",
    "h": "44.8373"
  },
  {
    "t": "18.6193",
    "h": "43.2267"
  },
  {
    "t": "18.318",
    "h": "41.6267"
  },
  {
    "t": "18.0187",
    "h": "41.816"
  },
  {
    "t": "17.7347",
    "h": "41.5253"
  },
  {
    "t": "17.448",
    "h": "40.8093"
  },
  {
    "t": "17.1753",
    "h": "40.5"
  },
  {
    "t": "16.9267",
    "h": "39.7133"
  },
  {
    "t": "16.66",
    "h": "39.4307"
  },
  {
    "t": "16.444",
    "h": "39.5587"
  },
  {
    "t": "16.182",
    "h": "40.1533"
  },
  {
    "t": "15.9493",
    "h": "41.0853"
  },
  {
    "t": "15.742",
    "h": "41.48"
  },
  {
    "t": "15.5887",
    "h": "40.9973"
  },
  {
    "t": "15.454",
    "h": "40.5773"
  },
  {
    "t": "15.3367",
    "h": "40.0093"
  },
  {
    "t": "15.24",
    "h": "39.8413"
  },
  {
    "t": "15.1193",
    "h": "39.7507"
  },
  {
    "t": "15.0067",
    "h": "39.56"
  },
  {
    "t": "14.8467",
    "h": "40.0253"
  },
  {
    "t": "14.7233",
    "h": "40.0653"
  },
  {
    "t": "14.6247",
    "h": "39.9693"
  },
  {
    "t": "14.526",
    "h": "40.0253"
  },
  {
    "t": "14.42",
    "h": "40.176"
  },
  {
    "t": "14.3233",
    "h": "40.1427"
  },
  {
    "t": "14.2333",
    "h": "40.2333"
  },
  {
    "t": "14.0873",
    "h": "40.604"
  },
  {
    "t": "13.8993",
    "h": "41.6347"
  },
  {
    "t": "13.7253",
    "h": "42.096"
  },
  {
    "t": "13.574",
    "h": "42.3627"
  },
  {
    "t": "13.4567",
    "h": "42.3013"
  },
  {
    "t": "13.348",
    "h": "42.2347"
  },
  {
    "t": "13.25",
    "h": "42.2587"
  },
  {
    "t": "13.1513",
    "h": "42.2133"
  },
  {
    "t": "13.042",
    "h": "42.9467"
  },
  {
    "t": "12.892",
    "h": "43.7893"
  },
  {
    "t": "12.7327",
    "h": "44.5893"
  },
  {
    "t": "12.6113",
    "h": "45.3013"
  },
  {
    "t": "12.4827",
    "h": "45.4453"
  },
  {
    "t": "12.38",
    "h": "45.7867"
  },
  {
    "t": "12.2667",
    "h": "46.24"
  },
  {
    "t": "12.2767",
    "h": "45.9227"
  },
  {
    "t": "12.3833",
    "h": "45.472"
  },
  {
    "t": "12.5627",
    "h": "44.968"
  },
  {
    "t": "12.8427",
    "h": "44.08"
  },
  {
    "t": "13.2287",
    "h": "43.616"
  },
  {
    "t": "13.7113",
    "h": "43.528"
  },
  {
    "t": "14.244",
    "h": "43.9973"
  },
  {
    "t": "14.8547",
    "h": "43.8507"
  },
  {
    "t": "15.5147",
    "h": "43.3707"
  },
  {
    "t": "16.2293",
    "h": "42.6187"
  },
  {
    "t": "17.0047",
    "h": "41.9707"
  },
  {
    "t": "17.812",
    "h": "41.1653"
  },
  {
    "t": "18.6393",
    "h": "40.5707"
  },
  {
    "t": "19.4273",
    "h": "40.3173"
  },
  {
    "t": "20.1127",
    "h": "39.5093"
  },
  {
    "t": "20.7733",
    "h": "38.3933"
  },
  {
    "t": "21.4267",
    "h": "37.228"
  },
  {
    "t": "22.0747",
    "h": "36.7307"
  },
  {
    "t": "22.7133",
    "h": "36.2987"
  },
  {
    "t": "23.348",
    "h": "35.3107"
  },
  {
    "t": "23.9427",
    "h": "34.8067"
  },
  {
    "t": "24.4907",
    "h": "34.464"
  },
  {
    "t": "25.0467",
    "h": "33.9347"
  },
  {
    "t": "25.5333",
    "h": "33.5413"
  },
  {
    "t": "26.024",
    "h": "33.0533"
  },
  {
    "t": "26.548",
    "h": "32.78"
  },
  {
    "t": "27.076",
    "h": "32.0707"
  },
  {
    "t": "27.576",
    "h": "31.4453"
  },
  {
    "t": "27.9827",
    "h": "31.2787"
  },
  {
    "t": "28.324",
    "h": "31.312"
  },
  {
    "t": "28.6653",
    "h": "31.1507"
  },
  {
    "t": "28.936",
    "h": "31.0947"
  },
  {
    "t": "29.128",
    "h": "30.68"
  },
  {
    "t": "29.156",
    "h": "29.7387"
  },
  {
    "t": "29.124",
    "h": "29.508"
  },
  {
    "t": "28.9947",
    "h": "29.1347"
  },
  {
    "t": "28.8427",
    "h": "28.108"
  },
  {
    "t": "28.58",
    "h": "26.408"
  },
  {
    "t": "28.192",
    "h": "26.1747"
  },
  {
    "t": "27.7693",
    "h": "25.5173"
  },
  {
    "t": "27.3813",
    "h": "25.784"
  },
  {
    "t": "26.9933",
    "h": "25.984"
  },
  {
    "t": "26.6387",
    "h": "26.4973"
  },
  {
    "t": "26.3027",
    "h": "27.0773"
  },
  {
    "t": "25.9133",
    "h": "27.7587"
  },
  {
    "t": "25.5333",
    "h": "28.26"
  },
  {
    "t": "25.164",
    "h": "28.3813"
  },
  {
    "t": "24.816",
    "h": "28.3707"
  },
  {
    "t": "24.4427",
    "h": "28.4253"
  },
  {
    "t": "24.0693",
    "h": "28.9533"
  },
  {
    "t": "23.716",
    "h": "29.0027"
  },
  {
    "t": "23.4213",
    "h": "29.2493"
  },
  {
    "t": "23.1293",
    "h": "30.6427"
  },
  {
    "t": "22.848",
    "h": "31.1933"
  },
  {
    "t": "22.5427",
    "h": "31.6333"
  },
  {
    "t": "22.2693",
    "h": "31.8773"
  },
  {
    "t": "21.9907",
    "h": "32.6133"
  },
  {
    "t": "21.7507",
    "h": "33.2547"
  },
  {
    "t": "21.4787",
    "h": "33.6027"
  },
  {
    "t": "21.2187",
    "h": "33.5493"
  },
  {
    "t": "20.9587",
    "h": "33.7533"
  },
  {
    "t": "20.688",
    "h": "33.884"
  },
  {
    "t": "20.454",
    "h": "34.6653"
  },
  {
    "t": "20.2007",
    "h": "35.1987"
  },
  {
    "t": "19.9473",
    "h": "35.556"
  },
  {
    "t": "19.7567",
    "h": "35.5667"
  },
  {
    "t": "19.544",
    "h": "36.1333"
  },
  {
    "t": "19.3247",
    "h": "36.2187"
  },
  {
    "t": "19.1187",
    "h": "36.5773"
  },
  {
    "t": "18.8967",
    "h": "36.9747"
  },
  {
    "t": "18.666",
    "h": "37.408"
  },
  {
    "t": "18.4427",
    "h": "37.544"
  },
  {
    "t": "18.2553",
    "h": "37.8173"
  },
  {
    "t": "18.0553",
    "h": "37.82"
  },
  {
    "t": "17.8667",
    "h": "38.2147"
  },
  {
    "t": "17.6107",
    "h": "38.6"
  },
  {
    "t": "17.4287",
    "h": "39.2067"
  },
  {
    "t": "17.2487",
    "h": "39.3587"
  },
  {
    "t": "17.0773",
    "h": "39.3947"
  },
  {
    "t": "16.966",
    "h": "38.7893"
  },
  {
    "t": "16.88",
    "h": "38.4107"
  },
  {
    "t": "16.7873",
    "h": "38.5307"
  },
  {
    "t": "16.632",
    "h": "38.912"
  },
  {
    "t": "16.5",
    "h": "39.3627"
  },
  {
    "t": "16.34",
    "h": "39.9493"
  },
  {
    "t": "16.1653",
    "h": "40.1267"
  },
  {
    "t": "15.9867",
    "h": "40.572"
  },
  {
    "t": "15.8407",
    "h": "40.7053"
  },
  {
    "t": "15.7133",
    "h": "41.6107"
  },
  {
    "t": "15.564",
    "h": "41.76"
  },
  {
    "t": "15.4713",
    "h": "41.1627"
  },
  {
    "t": "15.3867",
    "h": "40.9187"
  },
  {
    "t": "15.312",
    "h": "40.8387"
  },
  {
    "t": "15.2467",
    "h": "40.5027"
  },
  {
    "t": "15.1933",
    "h": "40.3747"
  },
  {
    "t": "15.1793",
    "h": "40.324"
  },
  {
    "t": "15.19",
    "h": "40.9"
  },
  {
    "t": "15.284",
    "h": "40.5973"
  },
  {
    "t": "15.4373",
    "h": "40.1653"
  },
  {
    "t": "15.7033",
    "h": "39.2213"
  },
  {
    "t": "16.026",
    "h": "38.6587"
  },
  {
    "t": "16.3293",
    "h": "38.444"
  },
  {
    "t": "16.6507",
    "h": "38.1693"
  },
  {
    "t": "17.1553",
    "h": "38.1493"
  },
  {
    "t": "17.7287",
    "h": "38.724"
  },
  {
    "t": "18.236",
    "h": "38.7853"
  },
  {
    "t": "18.7393",
    "h": "38.676"
  },
  {
    "t": "19.276",
    "h": "38.4733"
  },
  {
    "t": "19.816",
    "h": "38.0707"
  },
  {
    "t": "20.376",
    "h": "37.5387"
  },
  {
    "t": "20.8707",
    "h": "36.96"
  },
  {
    "t": "21.3227",
    "h": "36.6867"
  },
  {
    "t": "21.8373",
    "h": "36.2547"
  },
  {
    "t": "22.3187",
    "h": "35.9093"
  },
  {
    "t": "22.8173",
    "h": "35.6787"
  },
  {
    "t": "23.3653",
    "h": "34.8133"
  },
  {
    "t": "23.9013",
    "h": "34.2093"
  },
  {
    "t": "24.232",
    "h": "33.5853"
  },
  {
    "t": "24.3547",
    "h": "33.596"
  },
  {
    "t": "24.204",
    "h": "34.8453"
  },
  {
    "t": "24.1747",
    "h": "35.0507"
  },
  {
    "t": "24.164",
    "h": "34.896"
  },
  {
    "t": "24.068",
    "h": "34.5467"
  },
  {
    "t": "23.9333",
    "h": "34.4387"
  },
  {
    "t": "23.7027",
    "h": "35.484"
  },
  {
    "t": "23.464",
    "h": "37.416"
  },
  {
    "t": "23.3107",
    "h": "38.8747"
  },
  {
    "t": "23.236",
    "h": "39.764"
  },
  {
    "t": "23.1013",
    "h": "40.62"
  },
  {
    "t": "22.9627",
    "h": "40.0693"
  },
  {
    "t": "22.8653",
    "h": "37.776"
  },
  {
    "t": "22.7573",
    "h": "37.5987"
  },
  {
    "t": "22.652",
    "h": "39.604"
  },
  {
    "t": "22.536",
    "h": "39.8213"
  },
  {
    "t": "22.3853",
    "h": "40.0787"
  },
  {
    "t": "22.2547",
    "h": "40.72"
  },
  {
    "t": "22.1067",
    "h": "40.9187"
  },
  {
    "t": "21.952",
    "h": "40.06"
  },
  {
    "t": "21.78",
    "h": "39.5973"
  },
  {
    "t": "21.6507",
    "h": "40.3653"
  },
  {
    "t": "21.5307",
    "h": "40.528"
  },
  {
    "t": "21.3787",
    "h": "41.1027"
  },
  {
    "t": "21.22",
    "h": "41.4667"
  },
  {
    "t": "21.0013",
    "h": "41.984"
  },
  {
    "t": "20.8227",
    "h": "42.3173"
  },
  {
    "t": "20.6387",
    "h": "42.448"
  },
  {
    "t": "20.4533",
    "h": "42.9227"
  },
  {
    "t": "20.2507",
    "h": "43.4933"
  },
  {
    "t": "20.028",
    "h": "43.8773"
  },
  {
    "t": "19.8233",
    "h": "44.08"
  },
  {
    "t": "19.6273",
    "h": "44.5307"
  },
  {
    "t": "19.452",
    "h": "45.184"
  },
  {
    "t": "19.2647",
    "h": "46.1787"
  },
  {
    "t": "19.09",
    "h": "46.7467"
  },
  {
    "t": "18.9027",
    "h": "46.7227"
  },
  {
    "t": "18.6867",
    "h": "46.6027"
  },
  {
    "t": "18.4707",
    "h": "45.928"
  },
  {
    "t": "18.2487",
    "h": "44.5947"
  },
  {
    "t": "18.0333",
    "h": "44.144"
  },
  {
    "t": "17.778",
    "h": "44.2027"
  },
  {
    "t": "17.532",
    "h": "44.7787"
  },
  {
    "t": "17.3247",
    "h": "43.9573"
  },
  {
    "t": "17.1193",
    "h": "44.4133"
  },
  {
    "t": "16.8487",
    "h": "45.7093"
  },
  {
    "t": "16.522",
    "h": "46.464"
  },
  {
    "t": "16.2933",
    "h": "46.2027"
  },
  {
    "t": "16.1753",
    "h": "45.7893"
  },
  {
    "t": "16.0633",
    "h": "45.44"
  },
  {
    "t": "15.9393",
    "h": "46.2693"
  },
  {
    "t": "15.7533",
    "h": "45.1253"
  },
  {
    "t": "15.5247",
    "h": "45.232"
  },
  {
    "t": "15.2333",
    "h": "46.3013"
  },
  {
    "t": "14.9847",
    "h": "47.176"
  },
  {
    "t": "14.816",
    "h": "47.232"
  },
  {
    "t": "14.7493",
    "h": "46.3973"
  },
  {
    "t": "14.7033",
    "h": "46.4667"
  },
  {
    "t": "14.5767",
    "h": "47.3253"
  },
  {
    "t": "14.4067",
    "h": "47.4453"
  },
  {
    "t": "14.3053",
    "h": "47.2827"
  },
  {
    "t": "14.17",
    "h": "47.3387"
  },
  {
    "t": "14.0867",
    "h": "47.1733"
  },
  {
    "t": "14.0113",
    "h": "47.368"
  },
  {
    "t": "13.9533",
    "h": "46.976"
  },
  {
    "t": "13.7927",
    "h": "48.3573"
  },
  {
    "t": "13.5907",
    "h": "48.904"
  },
  {
    "t": "13.506",
    "h": "48.5387"
  },
  {
    "t": "13.4333",
    "h": "48.6133"
  },
  {
    "t": "13.3493",
    "h": "48.784"
  },
  {
    "t": "13.28",
    "h": "48.6107"
  },
  {
    "t": "13.2167",
    "h": "48.584"
  },
  {
    "t": "13.144",
    "h": "49.1387"
  },
  {
    "t": "13.11",
    "h": "49.232"
  },
  {
    "t": "13.1813",
    "h": "48.76"
  },
  {
    "t": "13.322",
    "h": "47.848"
  },
  {
    "t": "13.4867",
    "h": "48.256"
  },
  {
    "t": "13.7147",
    "h": "47.472"
  },
  {
    "t": "14.024",
    "h": "46.6507"
  },
  {
    "t": "14.386",
    "h": "45.7707"
  },
  {
    "t": "14.7747",
    "h": "45.08"
  },
  {
    "t": "15.2407",
    "h": "44.6773"
  },
  {
    "t": "15.792",
    "h": "44.5067"
  },
  {
    "t": "16.3973",
    "h": "44.16"
  },
  {
    "t": "16.9773",
    "h": "43.7787"
  },
  {
    "t": "17.5573",
    "h": "44.0773"
  },
  {
    "t": "18.0627",
    "h": "44.2907"
  },
  {
    "t": "18.4133",
    "h": "44.3653"
  },
  {
    "t": "18.8693",
    "h": "44.568"
  },
  {
    "t": "19.3433",
    "h": "44.4933"
  },
  {
    "t": "19.744",
    "h": "44.0613"
  },
  {
    "t": "20.1767",
    "h": "43.904"
  },
  {
    "t": "20.668",
    "h": "44.3173"
  },
  {
    "t": "21.1733",
    "h": "45.216"
  },
  {
    "t": "21.5867",
    "h": "45.592"
  },
  {
    "t": "21.9347",
    "h": "45.5173"
  },
  {
    "t": "22.2227",
    "h": "45.1253"
  },
  {
    "t": "22.5587",
    "h": "45.272"
  },
  {
    "t": "22.7933",
    "h": "44.744"
  },
  {
    "t": "23.1293",
    "h": "43.7627"
  },
  {
    "t": "23.5333",
    "h": "43.2747"
  },
  {
    "t": "23.748",
    "h": "42.3893"
  },
  {
    "t": "23.9747",
    "h": "42"
  },
  {
    "t": "24.0667",
    "h": "41.8347"
  },
  {
    "t": "24.268",
    "h": "41.768"
  },
  {
    "t": "24.3893",
    "h": "41.72"
  },
  {
    "t": "24.4107",
    "h": "42.0107"
  },
  {
    "t": "24.3307",
    "h": "43.1467"
  },
  {
    "t": "24.1667",
    "h": "44.0107"
  },
  {
    "t": "23.98",
    "h": "44.3147"
  },
  {
    "t": "23.7227",
    "h": "44.9173"
  },
  {
    "t": "23.3533",
    "h": "46.7627"
  }
]